authclient/__init__.py
authclient/client.py
authclient-1.0.dist-info/METADATA
authclient-1.0.dist-info/WHEEL
authclient-1.0.dist-info/top_level.txt
authclient-1.0.dist-info/RECORD
