Metadata-Version: 1.0
Name: authclient
Version: 1.0
Summary: Simple authentication client
Home-page: https://git.yurzs.dev/yurzs/authclient
Author: UNKNOWN
Author-email: UNKNOWN
License: UNKNOWN
Platform: UNKNOWN
